pinnx/__init__.py
pinnx/_trainer.py
pinnx/callbacks.py
pinnx/fnspace.py
pinnx/grad.py
pinnx/metrics.py
pinnx/geometry/__init__.py
pinnx/geometry/base.py
pinnx/geometry/geometry_1d.py
pinnx/geometry/geometry_2d.py
pinnx/geometry/geometry_3d.py
pinnx/geometry/geometry_nd.py
pinnx/geometry/pointcloud.py
pinnx/geometry/timedomain.py
pinnx/icbc/__init__.py
pinnx/icbc/base.py
pinnx/icbc/boundary_conditions.py
pinnx/icbc/initial_conditions.py
pinnx/nn/__init__.py
pinnx/nn/base.py
pinnx/nn/convert.py
pinnx/nn/deeponet.py
pinnx/nn/deeponet_strategy.py
pinnx/nn/fnn.py
pinnx/nn/mionet.py
pinnx/nn/model.py
pinnx/problem/__init__.py
pinnx/problem/base.py
pinnx/problem/dataset_function.py
pinnx/problem/dataset_general.py
pinnx/problem/dataset_mf.py
pinnx/problem/dataset_quadruple.py
pinnx/problem/dataset_triple.py
pinnx/problem/fpde.py
pinnx/problem/ide.py
pinnx/problem/pde.py
pinnx/problem/pde_operator.py
pinnx/utils/__init__.py
pinnx/utils/_convert.py
pinnx/utils/_display.py
pinnx/utils/array_ops.py
pinnx/utils/external.py
pinnx/utils/internal.py
pinnx/utils/losses.py
pinnx/utils/sampler.py
pinnx/utils/sampling.py
pinnx/utils/transformers.py
pinnx-0.0.2.post20250107.dist-info/LICENSE
pinnx-0.0.2.post20250107.dist-info/METADATA
pinnx-0.0.2.post20250107.dist-info/WHEEL
pinnx-0.0.2.post20250107.dist-info/top_level.txt
pinnx-0.0.2.post20250107.dist-info/RECORD
