Metadata-Version: 2.1
Name: pinnx
Version: 0.0.2.post20250107
Summary: Physics-informed.
Home-page: https://github.com/chaobrain/pinnx
Author: PINNx Developers
Author-email: PINNx Developers <chao.brain@qq.com>
License: Apache-2.0 license
Project-URL: homepage, http://github.com/chaobrain/pinnx
Project-URL: repository, http://github.com/chaobrain/pinnx
Keywords: computational neuroscience,brain-inspired computation,brain dynamics programming
Classifier: Natural Language :: English
Classifier: Operating System :: OS Independent
Classifier: Development Status :: 4 - Beta
Classifier: Intended Audience :: Developers
Classifier: Intended Audience :: Science/Research
Classifier: Programming Language :: Python :: 3
Classifier: Programming Language :: Python :: 3.9
Classifier: Programming Language :: Python :: 3.10
Classifier: Programming Language :: Python :: 3.11
Classifier: Programming Language :: Python :: 3.12
Classifier: License :: OSI Approved :: Apache Software License
Classifier: Programming Language :: Python
Classifier: Topic :: Scientific/Engineering :: Bio-Informatics
Classifier: Topic :: Scientific/Engineering :: Mathematics
Classifier: Topic :: Scientific/Engineering :: Artificial Intelligence
Classifier: Topic :: Software Development :: Libraries
Requires-Python: >=3.9
License-File: LICENSE
Requires-Dist: numpy
Requires-Dist: jax
Requires-Dist: brainunit (>=0.0.3)
Requires-Dist: matplotlib
Requires-Dist: scipy
Requires-Dist: scikit-learn
Requires-Dist: brainstate
Requires-Dist: braintools
Requires-Dist: optax
Requires-Dist: scikit-optimize
Provides-Extra: cpu
Requires-Dist: jaxlib ; extra == 'cpu'
Provides-Extra: cuda12
Requires-Dist: jaxlib[cuda12] ; extra == 'cuda12'
Provides-Extra: testing
Requires-Dist: pytest ; extra == 'testing'
Provides-Extra: tpu
Requires-Dist: jaxlib[tpu] ; extra == 'tpu'
